paspymod/__init__.py
paspymod/funct_tools.py
paspymod/logger.py
paspymod/utility.py
paspymod-0.1.6.dist-info/LICENSE
paspymod-0.1.6.dist-info/METADATA
paspymod-0.1.6.dist-info/WHEEL
paspymod-0.1.6.dist-info/top_level.txt
paspymod-0.1.6.dist-info/RECORD
