Metadata-Version: 2.1
Name: paspymod
Version: 0.1.6
Summary: Centrify PAS REST API Module to run scripts
Home-page: https://github.com/ajskrilla/pas_py_mod
Author: Andrew Schilling
Author-email: andrew.schilling@centrify.com
License: UNKNOWN
Platform: UNKNOWN
Requires-Python: >=3.6
Requires-Dist: requests
Requires-Dist: centrify.dmc
Requires-Dist: cachetools
